README.txt
setup.py
downloadarx/__init__.py
downloadarx/downloadarx.py
downloadarx.egg-info/PKG-INFO
downloadarx.egg-info/SOURCES.txt
downloadarx.egg-info/dependency_links.txt
downloadarx.egg-info/requires.txt
downloadarx.egg-info/top_level.txt